navycut/__init__.py
navycut/__main__.py
navycut/boiler_create_app/__init__.py
navycut/boiler_create_app/admin.py
navycut/boiler_create_app/models.py
navycut/boiler_create_app/sister.py
navycut/boiler_create_app/urls.py
navycut/boiler_create_app/views.py
navycut/boiler_create_project/.gitignore
navycut/boiler_create_project/manage.py
navycut/boiler_create_project/project_dir___boiler_dir/asgi.py
navycut/boiler_create_project/project_dir___boiler_dir/settings.py
navycut/boiler_create_project/project_dir___boiler_dir/test.py
navycut/boiler_create_project/project_dir___boiler_dir/wsgi.py
navycut/boiler_create_project/templates/README.md
navycut/cli/__init__.py
navycut/cli/_exec_cli.py
navycut/command/__init__.py
navycut/conf/__init__.py
navycut/conf/global_settings.py
navycut/contrib/__init__.py
navycut/contrib/decorators.py
navycut/contrib/forms.py
navycut/contrib/admin/__init__.py
navycut/contrib/admin/sister.py
navycut/contrib/admin/urls.py
navycut/contrib/admin/views.py
navycut/contrib/admin/site/__init__.py
navycut/contrib/admin/site/forms.py
navycut/contrib/admin/site/views.py
navycut/contrib/auth/__init__.py
navycut/contrib/auth/decorators.py
navycut/contrib/auth/models.py
navycut/contrib/auth/sister.py
navycut/contrib/cors/__init__.py
navycut/contrib/cors/sister.py
navycut/contrib/mail/__init__.py
navycut/contrib/mail/sister.py
navycut/contrib/mail/backends/__init__.py
navycut/contrib/mail/backends/console.py
navycut/contrib/mail/backends/dummy.py
navycut/contrib/mail/backends/filebased.py
navycut/contrib/mail/backends/locmem.py
navycut/contrib/mail/backends/smtp.py
navycut/core/__init__.py
navycut/core/_helper_decorators.py
navycut/core/_reloader.py
navycut/core/_serving.py
navycut/core/app_config.py
navycut/datastructures/__init__.py
navycut/datastructures/_object.py
navycut/errors/__init__.py
navycut/errors/datastructure.py
navycut/errors/misc.py
navycut/errors/models.py
navycut/errors/server.py
navycut/helpers/__init__.py
Navycut-0.0.5.dist-info/LICENSE
Navycut-0.0.5.dist-info/METADATA
Navycut-0.0.5.dist-info/WHEEL
Navycut-0.0.5.dist-info/entry_points.txt
Navycut-0.0.5.dist-info/top_level.txt
Navycut-0.0.5.dist-info/RECORD
