Metadata-Version: 2.1
Name: Navycut
Version: 0.0.5
Summary: Fullstack web framework using flask
Home-page: https://github.com/flaskAio/navycut
Author: Aniket Sarkar
Author-email: aniketsarkar@yahoo.com
License: MIT
Keywords: flask,django,Navycut
Platform: any
Classifier: Development Status :: 5 - Production/Stable
Classifier: Environment :: Web Environment
Classifier: Framework :: Flask
Classifier: Intended Audience :: Developers
Classifier: License :: OSI Approved :: MIT License
Classifier: Operating System :: OS Independent
Classifier: Programming Language :: Python
Classifier: Programming Language :: Python :: 3
Classifier: Programming Language :: Python :: 3 :: Only
Classifier: Programming Language :: Python :: 3.6
Classifier: Programming Language :: Python :: 3.7
Classifier: Programming Language :: Python :: 3.8
Classifier: Programming Language :: Python :: 3.9
Classifier: Programming Language :: Python :: Implementation :: CPython
Classifier: Programming Language :: Python :: Implementation :: PyPy
Classifier: Topic :: Software Development :: Libraries :: Python Modules
Requires-Python: >=3.6,<4
License-File: LICENSE
Requires-Dist: Flask-Admin (>=1.5.8)
Requires-Dist: Flask-Bootstrap (>=3.3.7.1)
Requires-Dist: Flask-Cors (>=3.0.10)
Requires-Dist: flask-mailman (>=0.3.0)
Requires-Dist: Flask-Login (>=0.5.0)
Requires-Dist: Flask-Migrate (>=2.7.0)
Requires-Dist: Flask-SQLAlchemy (>=2.5.1)
Requires-Dist: Flask-WTF (>=0.15.1)
Requires-Dist: nc-console (>=0.0.4)
Requires-Dist: python-dotenv (>=0.17.1)
Requires-Dist: SQLAlchemy-JSONField (>=1.0.0)
Requires-Dist: WTForms (<=2.3.3)
Requires-Dist: WTForms-SQLAlchemy (>=0.2)
Requires-Dist: pillow (>=8.3.0)
Requires-Dist: Flask-Express (>=0.1.1)
